[{"id":0,"isMaxi":true,"isElectric":true,"length":24,"needsWashing":true,"needsRepair":false},{"id":1,"isMaxi":false,"isElectric":true,"length":12,"needsWashing":false,"needsRepair":true},{"id":2,"isMaxi":false,"isElectric":true,"length":12,"needsWashing":false,"needsRepair":false},{"id":3,"isMaxi":false,"isElectric":true,"length":12,"needsWashing":false,"needsRepair":false},{"id":4,"isMaxi":false,"isElectric":true,"length":18,"needsWashing":true,"needsRepair":true},{"id":5,"isMaxi":false,"isElectric":true,"length":12,"needsWashing":true,"needsRepair":false},{"id":6,"isMaxi":false,"isElectric":true,"length":18,"needsWashing":false,"needsRepair":false},{"id":7,"isMaxi":false,"isElectric":true,"length":18,"needsWashing":true,"needsRepair":false},{"id":8,"isMaxi":false,"isElectric":true,"length":12,"needsWashing":false,"needsRepair":true},{"id":9,"isMaxi":false,"isElectric":true,"length":12,"needsWashing":false,"needsRepair":false},{"id":10,"isMaxi":false,"isElectric":true,"length":18,"needsWashing":false,"needsRepair":false},{"id":11,"isMaxi":false,"isElectric":true,"length":12,"needsWashing":false,"needsRepair":true},{"id":12,"isMaxi":false,"isElectric":true,"length":18,"needsWashing":true,"needsRepair":false},{"id":13,"isMaxi":false,"isElectric":true,"length":12,"needsWashing":false,"needsRepair":false},{"id":14,"isMaxi":false,"isElectric":true,"length":12,"needsWashing":false,"needsRepair":false},{"id":15,"isMaxi":false,"isElectric":true,"length":18,"needsWashing":true,"needsRepair":true},{"id":16,"isMaxi":false,"isElectric":true,"length":12,"needsWashing":false,"needsRepair":false},{"id":17,"isMaxi":false,"isElectric":true,"length":18,"needsWashing":false,"needsRepair":false},{"id":18,"isMaxi":false,"isElectric":true,"length":12,"needsWashing":false,"needsRepair":false},{"id":19,"isMaxi":false,"isElectric":false,"length":12,"needsWashing":false,"needsRepair":false},{"id":20,"isMaxi":false,"isElectric":true,"length":18,"needsWashing":true,"needsRepair":true},{"id":21,"isMaxi":false,"isElectric":false,"length":18,"needsWashing":true,"needsRepair":false},{"id":22,"isMaxi":false,"isElectric":true,"length":12,"needsWashing":true,"needsRepair":false},{"id":23,"isMaxi":false,"isElectric":true,"length":18,"needsWashing":false,"needsRepair":false},{"id":24,"isMaxi":false,"isElectric":true,"length":12,"needsWashing":false,"needsRepair":false},{"id":25,"isMaxi":false,"isElectric":false,"length":12,"needsWashing":true,"needsRepair":false},{"id":26,"isMaxi":false,"isElectric":false,"length":18,"needsWashing":false,"needsRepair":false},{"id":27,"isMaxi":false,"isElectric":false,"length":12,"needsWashing":false,"needsRepair":false},{"id":28,"isMaxi":false,"isElectric":true,"length":18,"needsWashing":false,"needsRepair":false},{"id":29,"isMaxi":false,"isElectric":true,"length":18,"needsWashing":false,"needsRepair":false},{"id":30,"isMaxi":false,"isElectric":true,"length":18,"needsWashing":false,"needsRepair":false},{"id":31,"isMaxi":false,"isElectric":true,"length":18,"needsWashing":false,"needsRepair":false},{"id":32,"isMaxi":false,"isElectric":false,"length":12,"needsWashing":false,"needsRepair":false},{"id":33,"isMaxi":false,"isElectric":true,"length":18,"needsWashing":false,"needsRepair":false},{"id":34,"isMaxi":false,"isElectric":true,"length":18,"needsWashing":true,"needsRepair":false},{"id":35,"isMaxi":false,"isElectric":true,"length":18,"needsWashing":true,"needsRepair":false},{"id":36,"isMaxi":false,"isElectric":false,"length":18,"needsWashing":true,"needsRepair":false},{"id":37,"isMaxi":false,"isElectric":false,"length":12,"needsWashing":false,"needsRepair":false},{"id":38,"isMaxi":false,"isElectric":true,"length":12,"needsWashing":true,"needsRepair":false},{"id":39,"isMaxi":false,"isElectric":true,"length":18,"needsWashing":false,"needsRepair":false},{"id":40,"isMaxi":false,"isElectric":true,"length":12,"needsWashing":false,"needsRepair":false},{"id":41,"isMaxi":false,"isElectric":true,"length":18,"needsWashing":false,"needsRepair":false},{"id":42,"isMaxi":false,"isElectric":true,"length":12,"needsWashing":false,"needsRepair":false},{"id":43,"isMaxi":false,"isElectric":true,"length":18,"needsWashing":true,"needsRepair":false},{"id":44,"isMaxi":false,"isElectric":true,"length":18,"needsWashing":false,"needsRepair":false},{"id":45,"isMaxi":false,"isElectric":true,"length":12,"needsWashing":true,"needsRepair":false},{"id":46,"isMaxi":false,"isElectric":false,"length":12,"needsWashing":false,"needsRepair":false},{"id":47,"isMaxi":false,"isElectric":true,"length":12,"needsWashing":false,"needsRepair":false},{"id":48,"isMaxi":false,"isElectric":true,"length":18,"needsWashing":false,"needsRepair":false},{"id":49,"isMaxi":false,"isElectric":true,"length":12,"needsWashing":false,"needsRepair":false},{"id":50,"isMaxi":false,"isElectric":true,"length":12,"needsWashing":false,"needsRepair":false},{"id":51,"isMaxi":false,"isElectric":true,"length":18,"needsWashing":false,"needsRepair":false},{"id":52,"isMaxi":false,"isElectric":true,"length":18,"needsWashing":true,"needsRepair":false},{"id":53,"isMaxi":false,"isElectric":true,"length":12,"needsWashing":false,"needsRepair":false},{"id":54,"isMaxi":false,"isElectric":true,"length":18,"needsWashing":false,"needsRepair":false},{"id":55,"isMaxi":false,"isElectric":true,"length":12,"needsWashing":false,"needsRepair":false},{"id":56,"isMaxi":false,"isElectric":true,"length":18,"needsWashing":false,"needsRepair":false},{"id":57,"isMaxi":false,"isElectric":true,"length":12,"needsWashing":true,"needsRepair":false},{"id":58,"isMaxi":false,"isElectric":true,"length":18,"needsWashing":false,"needsRepair":false},{"id":59,"isMaxi":false,"isElectric":true,"length":18,"needsWashing":false,"needsRepair":true},{"id":60,"isMaxi":false,"isElectric":false,"length":18,"needsWashing":false,"needsRepair":false},{"id":61,"isMaxi":false,"isElectric":true,"length":12,"needsWashing":false,"needsRepair":false},{"id":62,"isMaxi":false,"isElectric":true,"length":12,"needsWashing":false,"needsRepair":false},{"id":63,"isMaxi":false,"isElectric":true,"length":12,"needsWashing":false,"needsRepair":false}]